reticker/__init__.py
reticker/reticker.py
reticker/config/__init__.py
reticker/config/blacklist/general.txt
reticker/config/blacklist/noisy.txt
reticker/config/blacklist/profanity.txt
reticker-3.1.5.dist-info/LICENSE
reticker-3.1.5.dist-info/METADATA
reticker-3.1.5.dist-info/WHEEL
reticker-3.1.5.dist-info/top_level.txt
reticker-3.1.5.dist-info/RECORD
