Metadata-Version: 2.1
Name: reticker
Version: 3.1.5
Summary: Use a regular expression to extract possible stock tickers from text
Home-page: https://github.com/impredicative/reticker/
Author: Ouroboros Chrysopoeia
Author-email: impredicative@users.noreply.github.com
Keywords: regex regexp stock text ticker
Classifier: Programming Language :: Python :: 3.8
Classifier: Programming Language :: Python :: 3.9
Classifier: License :: OSI Approved :: GNU Affero General Public License v3
Classifier: Topic :: Office/Business :: Financial :: Investment
Classifier: Topic :: Software Development :: Libraries :: Python Modules
Classifier: Topic :: Text Processing :: Filters
Requires-Python: >=3.8
License-File: LICENSE
